ntpu_slmtk/__init__.py
ntpu_slmtk/_slmtk.cp313-win_amd64.pyd
ntpu_slmtk/DLL_DIR/TTS_data_format.dll
ntpu_slmtk/DLL_DIR/asmjit.dll
ntpu_slmtk/DLL_DIR/c10.dll
ntpu_slmtk/DLL_DIR/fbgemm.dll
ntpu_slmtk/DLL_DIR/libFW2CHPOS.dll
ntpu_slmtk/DLL_DIR/libRBTN.dll
ntpu_slmtk/DLL_DIR/libSS.dll
ntpu_slmtk/DLL_DIR/libTTS.dll
ntpu_slmtk/DLL_DIR/libbp_lstm.dll
ntpu_slmtk/DLL_DIR/libcrfpp.dll
ntpu_slmtk/DLL_DIR/libdata_format_lstm.dll
ntpu_slmtk/DLL_DIR/libengtransx.dll
ntpu_slmtk/DLL_DIR/libiomp5md.dll
ntpu_slmtk/DLL_DIR/libiompstubs5md.dll
ntpu_slmtk/DLL_DIR/liblab2fea.dll
ntpu_slmtk/DLL_DIR/liblabparser.dll
ntpu_slmtk/DLL_DIR/libpaf_cnn.dll
ntpu_slmtk/DLL_DIR/libparser2transx.dll
ntpu_slmtk/DLL_DIR/libparser_example.dll
ntpu_slmtk/DLL_DIR/libpoly.dll
ntpu_slmtk/DLL_DIR/libprosody_gen_lstm.dll
ntpu_slmtk/DLL_DIR/libpsp_lstm.dll
ntpu_slmtk/DLL_DIR/libsptk.dll
ntpu_slmtk/DLL_DIR/libtonesandhi.dll
ntpu_slmtk/DLL_DIR/libworld.dll
ntpu_slmtk/DLL_DIR/torch.dll
ntpu_slmtk/DLL_DIR/torch_cpu.dll
ntpu_slmtk/DLL_DIR/torch_global_deps.dll
ntpu_slmtk/DLL_DIR/uv.dll
ntpu_slmtk-1.0.9.dist-info/METADATA
ntpu_slmtk-1.0.9.dist-info/WHEEL
ntpu_slmtk-1.0.9.dist-info/top_level.txt
ntpu_slmtk-1.0.9.dist-info/RECORD
