Metadata-Version: 2.4
Name: ntpu-slmtk
Version: 1.0.9
Summary: A speech and language processing toolkit with PyTorch/LibTorch backend for Mandarin.
Author: Benson Liang
Requires-Dist: pybind11>=2.10
Dynamic: author
Dynamic: requires-dist
Dynamic: summary
